fstatemachine.py
fstatemachine-1.1.0.dist-info/LICENSE
fstatemachine-1.1.0.dist-info/METADATA
fstatemachine-1.1.0.dist-info/WHEEL
fstatemachine-1.1.0.dist-info/top_level.txt
fstatemachine-1.1.0.dist-info/RECORD
