Metadata-Version: 2.1
Name: fstatemachine
Version: 1.1.0
Summary: Python finite state machine
Home-page: https://github.com/yakimka/fstatemachine
Author: yakimka
Author-email: ss.yakim@gmail.com
License: MIT
Platform: UNKNOWN
Classifier: Development Status :: 5 - Production/Stable
Classifier: Programming Language :: Python :: 3
Classifier: Intended Audience :: Developers
Classifier: License :: OSI Approved :: MIT License
Classifier: Topic :: Software Development :: Libraries
Classifier: Topic :: Utilities
Requires-Python: >=3.6
License-File: LICENSE
